MANIFEST.in
README.rst
requirements.txt
setup.py
test_requirements.txt
django_stopwatch.egg-info/PKG-INFO
django_stopwatch.egg-info/SOURCES.txt
django_stopwatch.egg-info/dependency_links.txt
django_stopwatch.egg-info/requires.txt
django_stopwatch.egg-info/top_level.txt
stopwatch/__init__.py
stopwatch/backends.py
stopwatch/errors.py
stopwatch/keybuilders.py
stopwatch/loader.py
stopwatch/middleware.py
stopwatch/models.py
tests/__init__.py
tests/settings.py
tests/test_backends.py
tests/test_keybuilders.py
tests/test_loader.py
tests/test_middleware.py