Metadata-Version: 1.0
Name: django-stopwatch
Version: 0.2
Summary: Django Stopwatch
